django_inventory_ve-0.1.0.dist-info/licenses/LICENSE
inventory/__init__.py
inventory/apps.py
inventory/conf.py
inventory/enums.py
inventory/api/serializers.py
inventory/api/urls.py
inventory/api/views.py
inventory/mgmt/commands/inventory_bootstrap_demo.py
inventory/migrations/0001_initial.py
inventory/models/config.py
inventory/models/item.py
inventory/models/move.py
inventory/models/valuation.py
inventory/models/warehouse.py
inventory/posting/adapters.py
inventory/posting/signals.py
inventory/tests/conftest.py
inventory/tests/test_receive_issue_posting.py
inventory/utils/costing.py
inventory/utils/money.py
django_inventory_ve-0.1.0.dist-info/METADATA
django_inventory_ve-0.1.0.dist-info/WHEEL
django_inventory_ve-0.1.0.dist-info/top_level.txt
django_inventory_ve-0.1.0.dist-info/RECORD
